MANIFEST.in
README.rst
setup.cfg
setup.py
zombie/__init__.py
zombie/browser.py
zombie/compat.py
zombie.egg-info/PKG-INFO
zombie.egg-info/SOURCES.txt
zombie.egg-info/dependency_links.txt
zombie.egg-info/top_level.txt
zombie/proxy/__init__.py
zombie/proxy/client.py
zombie/proxy/server.js
zombie/proxy/server.py
zombie/tests/__init__.py
zombie/tests/test_browser.py
zombie/tests/test_client.py
zombie/tests/test_server.py
zombie/tests/test_webserver.py
zombie/tests/webserver.py